resumeio_dl/__init__.py
resumeio_dl/cli.py
resumeio_dl/downloader.py
resumeio_dl-0.1.0.dist-info/licenses/LICENSE
resumeio_dl-0.1.0.dist-info/METADATA
resumeio_dl-0.1.0.dist-info/WHEEL
resumeio_dl-0.1.0.dist-info/entry_points.txt
resumeio_dl-0.1.0.dist-info/top_level.txt
resumeio_dl-0.1.0.dist-info/RECORD
