Metadata-Version: 2.4
Name: resumeio-dl
Version: 0.1.0
Summary: Download resumes from resume.io as PDF files
Home-page: https://github.com/yourusername/resumeio-dl
Author: Noreddine
Author-email: your.email@example.com
Classifier: Development Status :: 4 - Beta
Classifier: Intended Audience :: End Users/Desktop
Classifier: License :: OSI Approved :: MIT License
Classifier: Programming Language :: Python :: 3
Classifier: Programming Language :: Python :: 3.8
Classifier: Programming Language :: Python :: 3.9
Classifier: Programming Language :: Python :: 3.10
Classifier: Programming Language :: Python :: 3.11
Classifier: Topic :: Utilities
Requires-Python: >=3.8
License-File: LICENSE
Requires-Dist: Pillow>=9.0.0
Requires-Dist: pytesseract>=0.3.9
Requires-Dist: pypdf>=3.0.0
Requires-Dist: requests>=2.25.0
Dynamic: author
Dynamic: author-email
Dynamic: classifier
Dynamic: description
Dynamic: description-content-type
Dynamic: home-page
Dynamic: license-file
Dynamic: requires-dist
Dynamic: requires-python
Dynamic: summary
